tkadw/__init__.py
tkadw/__main__.py
tkadw/designer/__init__.py
tkadw/designer/__main__.py
tkadw/designer/builder.py
tkadw/designer/designer.py
tkadw/designer/designerframe.py
tkadw/doc.py
tkadw/game/__init__.py
tkadw/game/sprite.py
tkadw/game/surface.py
tkadw/game/window.py
tkadw/layout/__init__.py
tkadw/layout/column.py
tkadw/layout/flow.py
tkadw/layout/put.py
tkadw/layout/row.py
tkadw/plugins/__init__.py
tkadw/plugins/pygubu/__init__.py
tkadw/plugins/pygubu/builders.py
tkadw/utility/__init__.py
tkadw/utility/app.config
tkadw/utility/appconfig.py
tkadw/utility/dragarea.py
tkadw/windows/__init__.py
tkadw/windows/canvas/__init__.py
tkadw/windows/canvas/button.py
tkadw/windows/canvas/checkbox.py
tkadw/windows/canvas/drawengine.py
tkadw/windows/canvas/entry.py
tkadw/windows/canvas/frame.py
tkadw/windows/canvas/scrollbar.py
tkadw/windows/canvas/separator.py
tkadw/windows/canvas/textbox.py
tkadw/windows/canvas/titlebar.py
tkadw/windows/canvas/widget.py
tkadw/windows/fluent/__init__.py
tkadw/windows/fluent/button.py
tkadw/windows/fluent/entry.py
tkadw/windows/fluent/frame.py
tkadw/windows/fluent/GeneralSans-Regular.ttf
tkadw/windows/fluent/test.py
tkadw/windows/theme.py
tkadw/windows/widgets/__init__.py
tkadw/windows/widgets/adw.py
tkadw/windows/widgets/label.py
tkadw/windows/widgets/listbox.py
tkadw/windows/widgets/mdi.py
tkadw/windows/widgets/menubar.py
tkadw/windows/widgets/stack.py
tkadw/windows/widgets/task.py
tkadw/windows/widgets/toolbox.py
tkadw/windows/widgets/toplevel.py
tkadw-0.4.9.dist-info/METADATA
tkadw-0.4.9.dist-info/WHEEL
tkadw-0.4.9.dist-info/RECORD
