Metadata-Version: 2.1
Name: tkadw
Version: 0.4.9
Summary: extra for tkinter
License: MIT
Author: XiangQinxi
Author-email: 1379773753@qq.com
Requires-Python: >=3.6,<4.0
Classifier: License :: OSI Approved :: MIT License
Classifier: Programming Language :: Python :: 3
Classifier: Programming Language :: Python :: 3.6
Classifier: Programming Language :: Python :: 3.7
Classifier: Programming Language :: Python :: 3.8
Classifier: Programming Language :: Python :: 3.9
Classifier: Programming Language :: Python :: 3.10
Classifier: Programming Language :: Python :: 3.11
Requires-Dist: tkinter-dndr (>=0.0.5,<0.0.6)
Requires-Dist: tkinterflow (>=0.0.5,<0.0.6)
Project-URL: Documentation, https://tkadwite.netlify.app/
